setup.py
bin/roboant_server
roboant_server/__init__.py
roboant_server.egg-info/PKG-INFO
roboant_server.egg-info/SOURCES.txt
roboant_server.egg-info/dependency_links.txt
roboant_server.egg-info/not-zip-safe
roboant_server.egg-info/requires.txt
roboant_server.egg-info/top_level.txt