Metadata-Version: 1.0
Name: roboant-server
Version: 0.1
Summary: Server for the RoboAnt project
Home-page: http://github.com/d3kod/roboant
Author: Aleksandar Kodzhabashev
Author-email: akodzhabashev@gmail.com
License: MIT
Platform: UNKNOWN
